{"lastUsed":1731383514480,"path":"D:\/backEnd\/bootworkspace","projectCount":5,"recentFiles":[{"path":"\/boot01\/src\/test\/java\/com\/yedam\/app","parentWorkspace":"D:\/backEnd\/bootworkspace","name":"AopTests.java","lastModified":1729821926315,"locationURI":"file:\/D:\/backEnd\/bootworkspace\/boot01\/src\/test\/java\/com\/yedam\/app\/AopTests.java"},{"path":"\/boot01\/src\/main\/resources\/templates","parentWorkspace":"D:\/backEnd\/bootworkspace","name":"all.html","lastModified":1730093735778,"locationURI":"file:\/D:\/backEnd\/bootworkspace\/boot01\/src\/main\/resources\/templates\/all.html"},{"path":"\/boot01\/src\/main\/java\/com\/yedam\/app\/security\/service\/impl","parentWorkspace":"D:\/backEnd\/bootworkspace","name":"CustomerUserDetailsService.java","lastModified":1730088016431,"locationURI":"file:\/D:\/backEnd\/bootworkspace\/boot01\/src\/main\/java\/com\/yedam\/app\/security\/service\/impl\/CustomerUserDetailsService.java"},{"path":"\/boot01\/src\/main\/java\/com\/yedam\/app","parentWorkspace":"D:\/bootworkspace","name":"Boot01Application.java","lastModified":1729575680366,"locationURI":"file:\/D:\/bootworkspace\/boot01\/src\/main\/java\/com\/yedam\/app\/Boot01Application.java"},{"path":"\/boot01\/src\/main\/resources\/mapper\/user","parentWorkspace":"D:\/backEnd\/bootworkspace","name":"UserMapper.xml","lastModified":1730088016431,"locationURI":"file:\/D:\/backEnd\/bootworkspace\/boot01\/src\/main\/resources\/mapper\/user\/UserMapper.xml"},{"path":"\/boot_board\/src\/main\/java\/com\/yedam\/app\/board\/mapper","parentWorkspace":"D:\/backEnd\/bootworkspace","name":"BoardMapper.java","lastModified":1730102424146,"locationURI":"file:\/D:\/backEnd\/bootworkspace\/boot_board\/src\/main\/java\/com\/yedam\/app\/board\/mapper\/BoardMapper.java"},{"path":"\/boot_board\/src\/main\/resources\/templates\/board","parentWorkspace":"D:\/backEnd\/bootworkspace","name":"boardInsert.html","lastModified":1730173049677,"locationURI":"file:\/D:\/backEnd\/bootworkspace\/boot_board\/src\/main\/resources\/templates\/board\/boardInsert.html"},{"path":"\/Exam01\/src\/main\/java\/com\/yedam\/app\/book\/web","parentWorkspace":"D:\/backEnd\/bootworkspace","name":"BookController.java","lastModified":1730189054935,"locationURI":"file:\/C:\/Users\/admin\/Desktop\/Exam01\/src\/main\/java\/com\/yedam\/app\/book\/web\/BookController.java"},{"path":"\/boot01\/src\/main\/resources","parentWorkspace":"D:\/bootworkspace","name":"application.properties","lastModified":1730158910677,"locationURI":"file:\/D:\/bootworkspace\/boot01\/src\/main\/resources\/application.properties"},{"path":"\/boot01\/src\/main\/java\/com\/yedam\/app\/emp\/service","parentWorkspace":"D:\/bootworkspace","name":"EmpService.java","lastModified":1729741922772,"locationURI":"file:\/D:\/bootworkspace\/boot01\/src\/main\/java\/com\/yedam\/app\/emp\/service\/EmpService.java"},{"path":"\/jpa\/src\/main\/resources","parentWorkspace":"D:\/backEnd\/bootworkspace","name":"application.properties","lastModified":1731378934995,"locationURI":"file:\/D:\/backEnd\/bootworkspace\/jpa\/src\/main\/resources\/application.properties"},{"path":"\/Exam01\/src\/main\/java\/com\/yedam\/app\/book\/service","parentWorkspace":"D:\/backEnd\/bootworkspace","name":"BookVO.java","lastModified":1730182714860,"locationURI":"file:\/C:\/Users\/admin\/Desktop\/Exam01\/src\/main\/java\/com\/yedam\/app\/book\/service\/BookVO.java"},{"path":"\/boot01\/src\/main\/java\/com\/yedam\/app\/aop\/service","parentWorkspace":"D:\/backEnd\/bootworkspace","name":"AaaService.java","lastModified":1729821465883,"locationURI":"file:\/D:\/backEnd\/bootworkspace\/boot01\/src\/main\/java\/com\/yedam\/app\/aop\/service\/AaaService.java"},{"path":"\/boot_board\/src\/main\/resources","parentWorkspace":"D:\/backEnd\/bootworkspace","name":"application.properties","lastModified":1730166300449,"locationURI":"file:\/D:\/backEnd\/bootworkspace\/boot_board\/src\/main\/resources\/application.properties"},{"path":"\/boot01\/src\/main\/java\/com\/yedam\/app\/upload\/web","parentWorkspace":"D:\/backEnd\/bootworkspace","name":"UploadController.java","lastModified":1729842685076,"locationURI":"file:\/D:\/backEnd\/bootworkspace\/boot01\/src\/main\/java\/com\/yedam\/app\/upload\/web\/UploadController.java"},{"path":"\/boot01\/src\/main\/java\/com\/yedam\/app\/security\/service","parentWorkspace":"D:\/backEnd\/bootworkspace","name":"UserVO.java","lastModified":1730082478322,"locationURI":"file:\/D:\/backEnd\/bootworkspace\/boot01\/src\/main\/java\/com\/yedam\/app\/security\/service\/UserVO.java"},{"path":"\/boot01\/src\/main\/resources\/templates\/emp","parentWorkspace":"D:\/backEnd\/bootworkspace","name":"update.html","lastModified":1729741922772,"locationURI":"file:\/D:\/backEnd\/bootworkspace\/boot01\/src\/main\/resources\/templates\/emp\/update.html"},{"path":"\/boot01\/src\/main\/resources\/templates","parentWorkspace":"D:\/backEnd\/bootworkspace","name":"formUpload.html","lastModified":1729842683895,"locationURI":"file:\/D:\/backEnd\/bootworkspace\/boot01\/src\/main\/resources\/templates\/formUpload.html"},{"path":"\/boot_board\/src\/main\/java\/com\/yedam\/app\/board\/service","parentWorkspace":"D:\/backEnd\/bootworkspace","name":"BoardVO.java","lastModified":1730102424146,"locationURI":"file:\/D:\/backEnd\/bootworkspace\/boot_board\/src\/main\/java\/com\/yedam\/app\/board\/service\/BoardVO.java"},{"path":"\/boot01\/src\/main\/java\/com\/yedam\/app\/aop\/mapper","parentWorkspace":"D:\/backEnd\/bootworkspace","name":"AaaMapper.java","lastModified":1729821366378,"locationURI":"file:\/D:\/backEnd\/bootworkspace\/boot01\/src\/main\/java\/com\/yedam\/app\/aop\/mapper\/AaaMapper.java"},{"path":"\/boot01\/src\/main\/java\/com\/yedam\/app\/aop\/config","parentWorkspace":"D:\/backEnd\/bootworkspace","name":"BeforeAdvice.java","lastModified":1729820439535,"locationURI":"file:\/D:\/backEnd\/bootworkspace\/boot01\/src\/main\/java\/com\/yedam\/app\/aop\/config\/BeforeAdvice.java"},{"path":"\/boot01","parentWorkspace":"D:\/bootworkspace","name":"pom.xml","lastModified":1730088016431,"locationURI":"file:\/D:\/bootworkspace\/boot01\/pom.xml"},{"path":"\/boot01\/src\/main\/resources\/templates\/common\/fragments","parentWorkspace":"D:\/backEnd\/bootworkspace","name":"emp_header.html","lastModified":1729842683895,"locationURI":"file:\/D:\/backEnd\/bootworkspace\/boot01\/src\/main\/resources\/templates\/common\/fragments\/emp_header.html"},{"path":"\/boot01\/src\/main\/java\/com\/yedam\/app\/common\/web","parentWorkspace":"D:\/backEnd\/bootworkspace","name":"SecurityController.java","lastModified":1730094111512,"locationURI":"file:\/D:\/backEnd\/bootworkspace\/boot01\/src\/main\/java\/com\/yedam\/app\/common\/web\/SecurityController.java"},{"path":"\/boot01\/src\/main\/java\/com\/yedam\/app\/common\/config","parentWorkspace":"D:\/backEnd\/bootworkspace","name":"WebControllerAdvice.java","lastModified":1729741922772,"locationURI":"file:\/D:\/backEnd\/bootworkspace\/boot01\/src\/main\/java\/com\/yedam\/app\/common\/config\/WebControllerAdvice.java"},{"path":"\/jpa\/src\/main\/java\/com\/yedam\/app\/customer","parentWorkspace":"D:\/backEnd\/bootworkspace","name":"CustomerController.java","lastModified":1731378658978,"locationURI":"file:\/D:\/backEnd\/bootworkspace\/jpa\/src\/main\/java\/com\/yedam\/app\/customer\/CustomerController.java"},{"path":"\/boot01\/src\/main\/resources\/templates\/emp","parentWorkspace":"D:\/backEnd\/bootworkspace","name":"list.html","lastModified":1729837519727,"locationURI":"file:\/D:\/backEnd\/bootworkspace\/boot01\/src\/main\/resources\/templates\/emp\/list.html"},{"path":"\/boot01\/src\/main\/java\/com\/yedam\/app\/security\/config","parentWorkspace":"D:\/backEnd\/bootworkspace","name":"SpringSecurityConfig.java","lastModified":1730088017319,"locationURI":"file:\/D:\/backEnd\/bootworkspace\/boot01\/src\/main\/java\/com\/yedam\/app\/security\/config\/SpringSecurityConfig.java"},{"path":"\/Exam01\/src\/main\/java\/com\/yedam\/app\/book\/service\/impl","parentWorkspace":"D:\/backEnd\/bootworkspace","name":"BookServiceImpl.java","lastModified":1730188289399,"locationURI":"file:\/C:\/Users\/admin\/Desktop\/Exam01\/src\/main\/java\/com\/yedam\/app\/book\/service\/impl\/BookServiceImpl.java"},{"path":"\/boot_board\/src\/main\/java\/com\/yedam\/app\/board\/service\/impl","parentWorkspace":"D:\/backEnd\/bootworkspace","name":"BoardServiceImpl.java","lastModified":1730105015437,"locationURI":"file:\/D:\/backEnd\/bootworkspace\/boot_board\/src\/main\/java\/com\/yedam\/app\/board\/service\/impl\/BoardServiceImpl.java"},{"path":"\/jpa\/src\/main\/java\/com\/yedam\/app\/customer","parentWorkspace":"D:\/backEnd\/bootworkspace","name":"CustomerRepository.java","lastModified":1731376881238,"locationURI":"file:\/D:\/backEnd\/bootworkspace\/jpa\/src\/main\/java\/com\/yedam\/app\/customer\/CustomerRepository.java"},{"path":"\/Exam01\/src\/main\/java\/com\/yedam\/app\/book\/service","parentWorkspace":"D:\/backEnd\/bootworkspace","name":"BookService.java","lastModified":1730188276225,"locationURI":"file:\/C:\/Users\/admin\/Desktop\/Exam01\/src\/main\/java\/com\/yedam\/app\/book\/service\/BookService.java"},{"path":"\/boot_board\/src\/main\/resources\/templates\/common\/layouts","parentWorkspace":"D:\/backEnd\/bootworkspace","name":"board_layout.html","lastModified":1730166300449,"locationURI":"file:\/D:\/backEnd\/bootworkspace\/boot_board\/src\/main\/resources\/templates\/common\/layouts\/board_layout.html"},{"path":"\/Exam01\/src\/main\/resources\/templates\/book","parentWorkspace":"D:\/backEnd\/bootworkspace","name":"bookInsert.html","lastModified":1730189307414,"locationURI":"file:\/C:\/Users\/admin\/Desktop\/Exam01\/src\/main\/resources\/templates\/book\/bookInsert.html"},{"path":"\/boot01\/src\/main\/resources\/templates","parentWorkspace":"D:\/backEnd\/bootworkspace","name":"user.html","lastModified":1730088016431,"locationURI":"file:\/D:\/backEnd\/bootworkspace\/boot01\/src\/main\/resources\/templates\/user.html"},{"path":"\/boot01\/src\/main\/java\/com\/yedam\/app\/emp\/service\/impl","parentWorkspace":"D:\/bootworkspace","name":"EmpServiceImpl.java","lastModified":1729741923372,"locationURI":"file:\/D:\/bootworkspace\/boot01\/src\/main\/java\/com\/yedam\/app\/emp\/service\/impl\/EmpServiceImpl.java"},{"path":"\/boot01\/src\/main\/java\/com\/yedam\/app\/common\/web","parentWorkspace":"D:\/backEnd\/bootworkspace","name":"ThymeleafController.java","lastModified":1729654032184,"locationURI":"file:\/D:\/backEnd\/bootworkspace\/boot01\/src\/main\/java\/com\/yedam\/app\/common\/web\/ThymeleafController.java"},{"path":"\/Exam01\/src\/main\/resources\/templates\/book","parentWorkspace":"D:\/backEnd\/bootworkspace","name":"bookList.html","lastModified":1730187422403,"locationURI":"file:\/C:\/Users\/admin\/Desktop\/Exam01\/src\/main\/resources\/templates\/book\/bookList.html"},{"path":"\/boot_board\/src\/main\/resources\/templates\/board","parentWorkspace":"D:\/backEnd\/bootworkspace","name":"boardInfo.html","lastModified":1730174675636,"locationURI":"file:\/D:\/backEnd\/bootworkspace\/boot_board\/src\/main\/resources\/templates\/board\/boardInfo.html"},{"path":"\/boot_board","parentWorkspace":"D:\/backEnd\/bootworkspace","name":"pom.xml","lastModified":1730162535654,"locationURI":"file:\/D:\/backEnd\/bootworkspace\/boot_board\/pom.xml"},{"path":"\/boot01\/src\/main\/resources\/templates\/emp","parentWorkspace":"D:\/backEnd\/bootworkspace","name":"insert.html","lastModified":1729741922772,"locationURI":"file:\/D:\/backEnd\/bootworkspace\/boot01\/src\/main\/resources\/templates\/emp\/insert.html"},{"path":"\/boot01\/src\/main\/resources\/templates","parentWorkspace":"D:\/backEnd\/bootworkspace","name":"admin.html","lastModified":1730088016431,"locationURI":"file:\/D:\/backEnd\/bootworkspace\/boot01\/src\/main\/resources\/templates\/admin.html"},{"path":"\/demo\/src\/main\/resources","parentWorkspace":"D:\/bootworkspace","name":"application.properties","lastModified":1729564419080,"locationURI":"file:\/C:\/Users\/admin\/Downloads\/demo\/demo\/src\/main\/resources\/application.properties"},{"path":"\/boot01\/src\/main\/java\/com\/yedam\/app\/security\/mapper","parentWorkspace":"D:\/backEnd\/bootworkspace","name":"UserMapper.java","lastModified":1730082658134,"locationURI":"file:\/D:\/backEnd\/bootworkspace\/boot01\/src\/main\/java\/com\/yedam\/app\/security\/mapper\/UserMapper.java"},{"path":"\/boot01\/src\/test\/java\/com\/yedam\/app","parentWorkspace":"D:\/backEnd\/bootworkspace","name":"SecurityTests.java","lastModified":1730088016431,"locationURI":"file:\/D:\/backEnd\/bootworkspace\/boot01\/src\/test\/java\/com\/yedam\/app\/SecurityTests.java"},{"path":"\/boot_board\/src\/main\/java\/com\/yedam\/app","parentWorkspace":"D:\/backEnd\/bootworkspace","name":"BootBoardApplication.java","lastModified":1730166300449,"locationURI":"file:\/D:\/backEnd\/bootworkspace\/boot_board\/src\/main\/java\/com\/yedam\/app\/BootBoardApplication.java"},{"path":"\/boot01\/src\/main\/resources\/templates\/thymeleaf","parentWorkspace":"D:\/backEnd\/bootworkspace","name":"second.html","lastModified":1729656598116,"locationURI":"file:\/D:\/backEnd\/bootworkspace\/boot01\/src\/main\/resources\/templates\/thymeleaf\/second.html"},{"path":"\/boot01\/src\/main\/resources\/templates\/common\/layouts","parentWorkspace":"D:\/backEnd\/bootworkspace","name":"default_layout.html","lastModified":1729837519727,"locationURI":"file:\/D:\/backEnd\/bootworkspace\/boot01\/src\/main\/resources\/templates\/common\/layouts\/default_layout.html"},{"path":"\/boot_board\/src\/main\/resources\/templates\/board","parentWorkspace":"D:\/backEnd\/bootworkspace","name":"boardList.html","lastModified":1730173315119,"locationURI":"file:\/D:\/backEnd\/bootworkspace\/boot_board\/src\/main\/resources\/templates\/board\/boardList.html"},{"path":"\/boot_board\/src\/main\/resources\/mapper\/board","parentWorkspace":"D:\/backEnd\/bootworkspace","name":"BoardMapper.xml","lastModified":1730169340433,"locationURI":"file:\/D:\/backEnd\/bootworkspace\/boot_board\/src\/main\/resources\/mapper\/board\/BoardMapper.xml"},{"path":"\/Exam01\/src\/main\/resources\/mapper\/book","parentWorkspace":"D:\/backEnd\/bootworkspace","name":"BookMapper.xml","lastModified":1730189349403,"locationURI":"file:\/C:\/Users\/admin\/Desktop\/Exam01\/src\/main\/resources\/mapper\/book\/BookMapper.xml"},{"path":"\/boot01\/src\/test\/java\/com\/yedam\/app","parentWorkspace":"D:\/backEnd\/bootworkspace","name":"Boot01ApplicationTests.java","lastModified":1729729777576,"locationURI":"file:\/D:\/backEnd\/bootworkspace\/boot01\/src\/test\/java\/com\/yedam\/app\/Boot01ApplicationTests.java"},{"path":"\/boot01\/src\/main\/java\/com\/yedam\/app\/emp\/mapper","parentWorkspace":"D:\/bootworkspace","name":"EmpMapper.java","lastModified":1729583611650,"locationURI":"file:\/D:\/bootworkspace\/boot01\/src\/main\/java\/com\/yedam\/app\/emp\/mapper\/EmpMapper.java"},{"path":"\/Exam01\/src\/main\/java\/com\/yedam\/app\/book\/mapper","parentWorkspace":"D:\/backEnd\/bootworkspace","name":"BookMapper.java","lastModified":1730188192112,"locationURI":"file:\/C:\/Users\/admin\/Desktop\/Exam01\/src\/main\/java\/com\/yedam\/app\/book\/mapper\/BookMapper.java"},{"path":"\/jpa\/src\/main\/resources","parentWorkspace":"D:\/backEnd\/bootworkspace","name":"application-dev.properties","lastModified":1731379166746,"locationURI":"file:\/D:\/backEnd\/bootworkspace\/jpa\/src\/main\/resources\/application-dev.properties"},{"path":"\/boot01\/src\/main\/resources\/mapper\/emp","parentWorkspace":"D:\/bootworkspace","name":"EmpMapper.xml","lastModified":1729741922772,"locationURI":"file:\/D:\/bootworkspace\/boot01\/src\/main\/resources\/mapper\/emp\/EmpMapper.xml"},{"path":"\/boot01\/src\/main\/java\/com\/yedam\/app\/security\/service","parentWorkspace":"D:\/backEnd\/bootworkspace","name":"LoginVO.java","lastModified":1730088017319,"locationURI":"file:\/D:\/backEnd\/bootworkspace\/boot01\/src\/main\/java\/com\/yedam\/app\/security\/service\/LoginVO.java"},{"path":"\/boot_board\/src\/main\/java\/com\/yedam\/app\/board\/web","parentWorkspace":"D:\/backEnd\/bootworkspace","name":"BoardController.java","lastModified":1730179415697,"locationURI":"file:\/D:\/backEnd\/bootworkspace\/boot_board\/src\/main\/java\/com\/yedam\/app\/board\/web\/BoardController.java"},{"path":"\/boot01\/src\/main\/java\/com\/yedam\/app\/emp\/web","parentWorkspace":"D:\/backEnd\/bootworkspace","name":"EmpController.java","lastModified":1729741922772,"locationURI":"file:\/D:\/backEnd\/bootworkspace\/boot01\/src\/main\/java\/com\/yedam\/app\/emp\/web\/EmpController.java"},{"path":"\/boot01\/src\/main\/java\/com\/yedam\/app\/emp\/web","parentWorkspace":"D:\/backEnd\/bootworkspace","name":"EmpRestController.java","lastModified":1729826533764,"locationURI":"file:\/D:\/backEnd\/bootworkspace\/boot01\/src\/main\/java\/com\/yedam\/app\/emp\/web\/EmpRestController.java"},{"path":"\/Exam01\/src\/main\/java\/com\/yedam\/app\/emp\/web","parentWorkspace":"D:\/backEnd\/bootworkspace","name":"EmpController.java","lastModified":1730182194720,"locationURI":"file:\/C:\/Users\/admin\/Desktop\/Exam01\/src\/main\/java\/com\/yedam\/app\/emp\/web\/EmpController.java"},{"path":"\/boot01\/src\/main\/resources\/templates\/common\/configs","parentWorkspace":"D:\/backEnd\/bootworkspace","name":"default_configs.html","lastModified":1729837519727,"locationURI":"file:\/D:\/backEnd\/bootworkspace\/boot01\/src\/main\/resources\/templates\/common\/configs\/default_configs.html"},{"path":"\/boot01\/src\/main\/resources\/templates\/thymeleaf","parentWorkspace":"D:\/backEnd\/bootworkspace","name":"first.html","lastModified":1729654025910,"locationURI":"file:\/D:\/backEnd\/bootworkspace\/boot01\/src\/main\/resources\/templates\/thymeleaf\/first.html"},{"path":"\/Exam01\/src\/main\/java\/com\/yedam\/app\/book\/service","parentWorkspace":"D:\/backEnd\/bootworkspace","name":"RentVO.java","lastModified":1730189419445,"locationURI":"file:\/C:\/Users\/admin\/Desktop\/Exam01\/src\/main\/java\/com\/yedam\/app\/book\/service\/RentVO.java"},{"path":"\/boot01\/src\/main\/java\/com\/yedam\/app\/aop\/service\/impl","parentWorkspace":"D:\/backEnd\/bootworkspace","name":"AaaServiceImpl.java","lastModified":1729822215383,"locationURI":"file:\/D:\/backEnd\/bootworkspace\/boot01\/src\/main\/java\/com\/yedam\/app\/aop\/service\/impl\/AaaServiceImpl.java"},{"path":"\/boot01\/src\/main\/java\/com\/yedam\/app\/upload\/config","parentWorkspace":"D:\/backEnd\/bootworkspace","name":"WebMvcConfig.java","lastModified":1729842977853,"locationURI":"file:\/D:\/backEnd\/bootworkspace\/boot01\/src\/main\/java\/com\/yedam\/app\/upload\/config\/WebMvcConfig.java"},{"path":"\/boot_board\/src\/main\/resources\/templates\/common\/fragments","parentWorkspace":"D:\/backEnd\/bootworkspace","name":"board_fragment.html","lastModified":1730167820163,"locationURI":"file:\/D:\/backEnd\/bootworkspace\/boot_board\/src\/main\/resources\/templates\/common\/fragments\/board_fragment.html"},{"path":"\/boot01\/src\/main\/resources\/templates","parentWorkspace":"D:\/backEnd\/bootworkspace","name":"upload.html","lastModified":1729842683895,"locationURI":"file:\/D:\/backEnd\/bootworkspace\/boot01\/src\/main\/resources\/templates\/upload.html"},{"path":"\/jpa\/src\/test\/java\/com\/yedam\/app","parentWorkspace":"D:\/backEnd\/bootworkspace","name":"CustomerRepositoryClient.java","lastModified":1731377318573,"locationURI":"file:\/D:\/backEnd\/bootworkspace\/jpa\/src\/test\/java\/com\/yedam\/app\/CustomerRepositoryClient.java"},{"path":"\/boot01\/src\/main\/java\/com\/yedam\/app\/emp\/service","parentWorkspace":"D:\/bootworkspace","name":"EmpVO.java","lastModified":1729737456280,"locationURI":"file:\/D:\/bootworkspace\/boot01\/src\/main\/java\/com\/yedam\/app\/emp\/service\/EmpVO.java"},{"path":"\/jpa\/src\/main\/java\/com\/yedam\/app\/customer","parentWorkspace":"D:\/backEnd\/bootworkspace","name":"Customer.java","lastModified":1731377297867,"locationURI":"file:\/D:\/backEnd\/bootworkspace\/jpa\/src\/main\/java\/com\/yedam\/app\/customer\/Customer.java"},{"path":"\/boot01\/src\/main\/resources\/templates\/emp","parentWorkspace":"D:\/backEnd\/bootworkspace","name":"info.html","lastModified":1729729777576,"locationURI":"file:\/D:\/backEnd\/bootworkspace\/boot01\/src\/main\/resources\/templates\/emp\/info.html"},{"path":"\/Exam01\/src\/main\/resources\/templates\/common\/fragments","parentWorkspace":"D:\/backEnd\/bootworkspace","name":"header.html","lastModified":1730184680019,"locationURI":"file:\/C:\/Users\/admin\/Desktop\/Exam01\/src\/main\/resources\/templates\/common\/fragments\/header.html"}]}